lol/__init__.py
lol/riot.py
lol/resource/__init__.py
lol/resource/account.py
lol/resource/champion.py
lol/resource/championmastery.py
lol/resource/league.py
lol/resource/lolstaticdata.py
lol/resource/lolstatus.py
lol/resource/masteries.py
lol/resource/match.py
lol/resource/proplay.py
lol/resource/spectator.py
lol/resource/summoner.py
lol/resource/tftleague.py
lol/resource/tftmatch.py
lol/resource/tftsummoner.py
lol/resource/thirdpartycode.py
lol/resource/tests/__init__.py
lol/resource/tests/test_account.py
lol/resource/tests/test_champion.py
lol/resource/tests/test_championmastery.py
lol/resource/tests/test_league.py
lol/resource/tests/test_lolstaticdata.py
lol/resource/tests/test_lolstatus.py
lol/resource/tests/test_masteries.py
lol/resource/tests/test_match.py
lol/resource/tests/test_pro.py
lol/resource/tests/test_spectator.py
lol/resource/tests/test_summoner.py
lol/resource/tests/test_tftleague.py
lol/resource/tests/test_thirdpartycode.py
lolwrapper-1.8.1.dist-info/METADATA
lolwrapper-1.8.1.dist-info/WHEEL
lolwrapper-1.8.1.dist-info/top_level.txt
lolwrapper-1.8.1.dist-info/RECORD
