Metadata-Version: 2.1
Name: lolwrapper
Version: 1.8.1
Summary: Riot API Wrapper
Home-page: https://github.com/brianjp93/lolapi
Author: Brian Perrett
Author-email: perrettbrian@gmail.com
Classifier: Programming Language :: Python :: 3
Classifier: License :: OSI Approved :: MIT License
Classifier: Operating System :: OS Independent
Requires-Python: >=3.6
Requires-Dist: requests
